CHANGES.txt
CONTRIBUTORS.txt
MANIFEST.in
README.txt
buildout.cfg
setup.py
plone/__init__.py
plone.recipe.haproxy.egg-info/PKG-INFO
plone.recipe.haproxy.egg-info/SOURCES.txt
plone.recipe.haproxy.egg-info/dependency_links.txt
plone.recipe.haproxy.egg-info/entry_points.txt
plone.recipe.haproxy.egg-info/namespace_packages.txt
plone.recipe.haproxy.egg-info/not-zip-safe
plone.recipe.haproxy.egg-info/requires.txt
plone.recipe.haproxy.egg-info/top_level.txt
plone/recipe/__init__.py
plone/recipe/haproxy/__init__.py
plone/recipe/haproxy/tests/__init__.py
plone/recipe/haproxy/tests/download.txt
plone/recipe/haproxy/tests/test_docs.py