Metadata-Version: 1.0
Name: plone.recipe.haproxy
Version: 1.1.2
Summary: Buildout recipe to install haproxy
Home-page: http://pypi.python.org/pypi/plone.recipe.haproxy
Author: Helge Tesdal
Author-email: tesdal@jarn.com
License: ZPL
Keywords: buildout haproxy proxy loadbalancer
Platform: UNKNOWN
Classifier: Framework :: Buildout
Classifier: Intended Audience :: Developers
Classifier: Topic :: Software Development :: Build Tools
